iso_week_date/__init__.py
iso_week_date/_base.py
iso_week_date/_patterns.py
iso_week_date/_utils.py
iso_week_date/isoweek.py
iso_week_date/isoweekdate.py
iso_week_date/pandas_utils.py
iso_week_date/polars_utils.py
iso_week_date/py.typed
iso_week_date/pydantic.py
iso_week_date-2.2.2.dist-info/METADATA
iso_week_date-2.2.2.dist-info/WHEEL
iso_week_date-2.2.2.dist-info/licenses/LICENSE
iso_week_date-2.2.2.dist-info/RECORD
