Metadata-Version: 2.4
Name: iso-week-date
Version: 2.2.2
Summary: Toolkit to work with str representing ISO Week date format
Project-URL: repository, https://github.com/fbruzzesi/iso-week-date
Project-URL: issue-tracker, https://github.com/fbruzzesi/iso-week-date/issues
Project-URL: documentation, https://fbruzzesi.github.io/iso-week-date/
Author: Francesco Bruzzesi
License: MIT License
License-File: LICENSE
Classifier: Development Status :: 5 - Production/Stable
Classifier: License :: OSI Approved :: MIT License
Classifier: Programming Language :: Python :: 3
Classifier: Programming Language :: Python :: 3.9
Classifier: Programming Language :: Python :: 3.10
Classifier: Programming Language :: Python :: 3.11
Classifier: Programming Language :: Python :: 3.12
Classifier: Programming Language :: Python :: 3.13
Classifier: Programming Language :: Python :: 3.14
Classifier: Programming Language :: Python :: Free Threading :: 2 - Beta
Classifier: Topic :: Software Development :: Libraries :: Python Modules
Classifier: Typing :: Typed
Requires-Python: >=3.9
Provides-Extra: all
Requires-Dist: pandas>=1.0.0; extra == 'all'
Requires-Dist: polars>=0.18.0; extra == 'all'
Requires-Dist: pydantic>=2.4.0; extra == 'all'
Provides-Extra: pandas
Requires-Dist: pandas>=1.0.0; extra == 'pandas'
Provides-Extra: polars
Requires-Dist: polars>=0.18.0; extra == 'polars'
Provides-Extra: pydantic
Requires-Dist: pydantic>=2.4.0; extra == 'pydantic'
